glossary/__init__.py
glossary/admin.py
glossary/apps.py
glossary/queryset.py
glossary/urls.py
glossary/utils.py
glossary/views.py
glossary/management/__init__.py
glossary/management/commands/__init__.py
glossary/management/commands/get_updates.py
glossary/management/commands/register.py
glossary/migrations/0001_initial.py
glossary/migrations/0002_auto_20170314_0850.py
glossary/migrations/0003_auto_20170504_0253.py
glossary/migrations/0004_academicgroup_dekid.py
glossary/migrations/0005_auto_20190131_0942.py
glossary/migrations/0006_auto_20190204_0853.py
glossary/migrations/0007_room_campus.py
glossary/migrations/0008_subdivision_type.py
glossary/migrations/0009_auto_20190414_1342.py
glossary/migrations/__init__.py
glossary/models/__init__.py
glossary/models/education.py
glossary/models/structure.py
glossary-0.4.13.dist-info/LICENSE.txt
glossary-0.4.13.dist-info/METADATA
glossary-0.4.13.dist-info/WHEEL
glossary-0.4.13.dist-info/top_level.txt
glossary-0.4.13.dist-info/RECORD
