Metadata-Version: 2.1
Name: glossary
Version: 0.4.13
Summary: Glossary with common Ionosphere data
Home-page: UNKNOWN
Author: dissw-team
Author-email: lab.dissw@gmail.com
Maintainer: Dmitry Shlagov
Maintainer-email: wessmoke@gmail.com
License: MIT
Platform: UNKNOWN
Classifier: Development Status :: 3 - Alpha
Classifier: Intended Audience :: Developers
Classifier: License :: OSI Approved :: MIT License
Classifier: Natural Language :: Russian
Classifier: Programming Language :: Python
Classifier: Programming Language :: Python :: 3
Classifier: Programming Language :: Python :: 3.5
Requires-Dist: setuptools
Requires-Dist: Django (>=1.10.6)
Requires-Dist: requests
Requires-Dist: django-mptt (==0.9.1)
